extraEncodings/__init__.py
extraEncodings/ciphers.py
extraEncodings/encodings.py
extraEncodings/encodingsGui.py
extraEncodings-1.5.7.2.dist-info/LICENSE
extraEncodings-1.5.7.2.dist-info/METADATA
extraEncodings-1.5.7.2.dist-info/WHEEL
extraEncodings-1.5.7.2.dist-info/top_level.txt
extraEncodings-1.5.7.2.dist-info/RECORD
